bowtie2_py/__main__.py
bowtie2_py/bowtie2
bowtie2_py/bowtie2.py
bowtie2_py/main.py
bowtie2_py/version
bowtie2_py/bin/AUTHORS
bowtie2_py/bin/BOWTIE2_VERSION
bowtie2_py/bin/LICENSE
bowtie2_py/bin/MANUAL
bowtie2_py/bin/MANUAL.markdown
bowtie2_py/bin/NEWS
bowtie2_py/bin/README.md
bowtie2_py/bin/TUTORIAL
bowtie2_py/bin/bowtie2
bowtie2_py/bin/bowtie2-align-l-debug.exe
bowtie2_py/bin/bowtie2-align-l.exe
bowtie2_py/bin/bowtie2-align-s-debug.exe
bowtie2_py/bin/bowtie2-align-s.exe
bowtie2_py/bin/bowtie2-build
bowtie2_py/bin/bowtie2-build-l-debug.exe
bowtie2_py/bin/bowtie2-build-l.exe
bowtie2_py/bin/bowtie2-build-s-debug.exe
bowtie2_py/bin/bowtie2-build-s.exe
bowtie2_py/bin/bowtie2-build.bat
bowtie2_py/bin/bowtie2-inspect
bowtie2_py/bin/bowtie2-inspect-l-debug.exe
bowtie2_py/bin/bowtie2-inspect-l.exe
bowtie2_py/bin/bowtie2-inspect-s-debug.exe
bowtie2_py/bin/bowtie2-inspect-s.exe
bowtie2_py/bin/bowtie2-inspect.bat
bowtie2_py/bin/bowtie2.bat
bowtie2_py/bin/doc/README
bowtie2_py/bin/doc/manual.html
bowtie2_py/bin/doc/style.css
bowtie2_py/bin/example/index/lambda_virus.1.bt2
bowtie2_py/bin/example/index/lambda_virus.2.bt2
bowtie2_py/bin/example/index/lambda_virus.3.bt2
bowtie2_py/bin/example/index/lambda_virus.4.bt2
bowtie2_py/bin/example/index/lambda_virus.rev.1.bt2
bowtie2_py/bin/example/index/lambda_virus.rev.2.bt2
bowtie2_py/bin/example/reads/combined_reads.bam
bowtie2_py/bin/example/reads/longreads.fq
bowtie2_py/bin/example/reads/reads_1.fq
bowtie2_py/bin/example/reads/reads_2.fq
bowtie2_py/bin/example/reads/simulate.pl
bowtie2_py/bin/example/reference/lambda_virus.fa
bowtie2_py/bin/scripts/bowtie2-hbb.sh
bowtie2_py/bin/scripts/convert_quals.pl
bowtie2_py/bin/scripts/gen_2b_occ_lookup.pl
bowtie2_py/bin/scripts/gen_occ_lookup.pl
bowtie2_py/bin/scripts/gen_solqual_lookup.pl
bowtie2_py/bin/scripts/infer_fraglen.pl
bowtie2_py/bin/scripts/make_a_thaliana_tair.sh
bowtie2_py/bin/scripts/make_b_taurus_UMD3.sh
bowtie2_py/bin/scripts/make_c_elegans.sh
bowtie2_py-2025.4.22.1.dist-info/METADATA
bowtie2_py-2025.4.22.1.dist-info/WHEEL
bowtie2_py-2025.4.22.1.dist-info/entry_points.txt
bowtie2_py-2025.4.22.1.dist-info/licenses/LICENSE
bowtie2_py-2025.4.22.1.dist-info/RECORD
